LICENSE
MANIFEST.in
README.rst
setup.cfg
setup.py
downstream_farmer/__init__.py
downstream_farmer/cli_stats.py
downstream_farmer/client.py
downstream_farmer/contract.py
downstream_farmer/exc.py
downstream_farmer/farmer.py
downstream_farmer/farmer_stats.py
downstream_farmer/shell.py
downstream_farmer/utils.py
downstream_farmer/version.py
downstream_farmer.egg-info/PKG-INFO
downstream_farmer.egg-info/SOURCES.txt
downstream_farmer.egg-info/dependency_links.txt
downstream_farmer.egg-info/entry_points.txt
downstream_farmer.egg-info/requires.txt
downstream_farmer.egg-info/top_level.txt
downstream_farmer/data/ca-bundle.crt