Metadata-Version: 1.1
Name: downstream-farmer
Version: 0.1.8
Summary: Client software for a Storj farmer
Home-page: https://github.com/Storj/downstream-farmer
Author: Storj Labs
Author-email: info@storj.io
License: The MIT License (MIT)
